[{"id":1,"firstName":"lucy","lastName":"smith","email":"lucy.smith@gmail.com","phone":"6048984511","over25":"checked","driversLicense":"4545bgr4","pickUp":"","dropOff":"","startDate":1648952537000,"endDate":1649211737000,"timestamp":1648952537000},{"id":2,"firstName":"alice","lastName":"samson","email":"alice@gmail.com","phone":"6048988461","over25":"checked","driversLicense":"4554vfr4","pickUp":"","dropOff":"","startDate":1650515873000,"endDate":1650947873000,"timestamp":1648952537000},{"id":"f8dc19e6-c547-4633-97ec-150173939b6f","firstName":"Sam","lastName":"Wilson","email":"sam@gmail.com","phone":"6045895441","over25":"checked","driversLicense":"56431560651","pickUp":"8am-9am","dropOff":"3pm-4pm","startDate":1652857200000,"endDate":1653030000000,"timestamp":1649186048911},{"id":"ddfce6e5-7eaf-48cd-b384-fc91d422ed6f","firstName":"Lucy","lastName":"Wightwick","email":"lucy_wightwick@hotmail.com","phone":"6049664689","over25":"checked","driversLicense":"snstyj","pickUp":"9am-10am","dropOff":"10am-11am","startDate":1654153200000,"endDate":1654326000000,"timestamp":1649188754413},{"id":"d84a1547-d48f-4036-b319-858460722288","firstName":"Lucy","lastName":"Wightwick","email":"lucy_wightwick@hotmail.com","phone":"6049664689","over25":"checked","driversLicense":"sfgrewg","pickUp":"8am-9am","dropOff":"4pm-5pm","startDate":1654326000000,"endDate":1654498800000,"timestamp":1649190923942},{"id":"c0892621-26d4-4509-808d-24cc8935796b","firstName":"Lucy","lastName":"Wightwick","email":"lucy_wightwick@hotmail.com","phone":"6049664689","over25":"checked","driversLicense":"sfgrewg","pickUp":"8am-9am","dropOff":"4pm-5pm","startDate":1655362800000,"endDate":1655535600000,"timestamp":1649194539698},{"id":"35a0fcbf-096f-40b6-b7cd-9e71cd0c8178","firstName":"Lucy","lastName":"Wightwick","email":"lucy_wightwick@hotmail.com","phone":"6049664689","over25":"checked","driversLicense":"fergrt","pickUp":"9am-10am","dropOff":"12pm-1pm","startDate":1657782000000,"endDate":1657954800000,"timestamp":1649195342229}]